wetlab/__init__.py
wetlab/models.py
wetlab/types.py
wetlab/migrations/0025_squashed.py
wetlab/migrations/0026_alter_biosample_artifacts_alter_techsample_artifacts.py
wetlab/migrations/0027_rename_treatment_add_donor.py
wetlab/migrations/0028_remove_combinationperturbation_compounds_and_more.py
wetlab/migrations/0029_artifactbiologic_biologic_artifactbiologic_biologic.py
wetlab/migrations/0030_lamindbv1.py
wetlab/migrations/0031_alter_biologic_space_alter_biosample_space_and_more.py
wetlab/migrations/0032_rename_aux_biologic__aux_rename_aux_biosample__aux_and_more.py
wetlab/migrations/0033_alter_biologic__aux_alter_biosample__aux_and_more.py
wetlab/migrations/0034_lamindbv1_part6.py
wetlab/migrations/0035_alter_biologic_targets_alter_compound_name_and_more.py
wetlab/migrations/0036_alter_artifactbiologic_options_and_more.py
wetlab/migrations/0037_rename__branch_code_biologic_branch_and_more.py
wetlab/migrations/0038_alter_biologic_branch_alter_biologic_space_and_more.py
wetlab/migrations/0039_alter_biologic_description_alter_biologic_synonyms_and_more.py
wetlab/migrations/0040_compound_canonical_smiles_compound_inchikey_and_more.py
wetlab/migrations/0041_alter_artifactbiologic_options_and_more.py
wetlab/migrations/0042_biologic_page_biosample_page_and_more.py
wetlab/migrations/0043_biologic_is_locked_biosample_is_locked_and_more.py
wetlab/migrations/0044_alter_biologic_is_locked_alter_biosample_is_locked_and_more.py
wetlab/migrations/0045_remove_biologic_page_remove_biosample_page_and_more.py
wetlab/migrations/0046_artifactgeneticperturbation_wetlab_arti_artifac_8731fa_idx.py
wetlab/migrations/0047_artifactperturbationtarget_wetlab_arti_artifac_2674c5_idx.py
wetlab/migrations/0048_remove_artifactbiologic_feature_ref_is_name_and_more.py
wetlab/migrations/0049_remove_biosample_artifacts_and_more.py
wetlab/migrations/0050_compoundperturbation_abbr_and_more.py
wetlab/migrations/0050_squashed.py
wetlab/migrations/__init__.py
wetlab-2.0.1.dist-info/WHEEL
wetlab-2.0.1.dist-info/METADATA
wetlab-2.0.1.dist-info/RECORD
