Metadata-Version: 2.3
Name: wetlab
Version: 2.0.1
Summary: Basic wetlab entities [`source <https://github.com/laminlabs/wetlab/blob/main/wetlab/models.py>`__].
Author-email: Lamin Labs <open-source@lamin.ai>
Requires-Dist: lamindb>=2.0a1,<3
Requires-Dist: bionty>=2.0a1,<3
Requires-Dist: pre-commit ; extra == "dev"
Requires-Dist: nox ; extra == "dev"
Requires-Dist: pytest>=6.0 ; extra == "dev"
Requires-Dist: pytest-cov ; extra == "dev"
Requires-Dist: nbproject_test>=0.4.1 ; extra == "dev"
Project-URL: Home, https://github.com/laminlabs/wetlab
Provides-Extra: dev
